odoo/addons/stock_picking_filter_lot/README.rst
odoo/addons/stock_picking_filter_lot/__init__.py
odoo/addons/stock_picking_filter_lot/__manifest__.py
odoo/addons/stock_picking_filter_lot/i18n/it.po
odoo/addons/stock_picking_filter_lot/i18n/pt_BR.po
odoo/addons/stock_picking_filter_lot/i18n/sl.po
odoo/addons/stock_picking_filter_lot/i18n/stock_picking_filter_lot.pot
odoo/addons/stock_picking_filter_lot/models/__init__.py
odoo/addons/stock_picking_filter_lot/models/stock_production_lot.py
odoo/addons/stock_picking_filter_lot/readme/CONTRIBUTORS.rst
odoo/addons/stock_picking_filter_lot/readme/DESCRIPTION.rst
odoo/addons/stock_picking_filter_lot/readme/USAGE.rst
odoo/addons/stock_picking_filter_lot/static/description/icon.png
odoo/addons/stock_picking_filter_lot/static/description/index.html
odoo/addons/stock_picking_filter_lot/views/stock_move_line_view.xml
odoo/addons/stock_picking_filter_lot/views/stock_picking_view.xml
odoo/addons/stock_picking_filter_lot/views/stock_scrap_view.xml
odoo12_addon_stock_picking_filter_lot-12.0.1.1.2.dist-info/METADATA
odoo12_addon_stock_picking_filter_lot-12.0.1.1.2.dist-info/WHEEL
odoo12_addon_stock_picking_filter_lot-12.0.1.1.2.dist-info/top_level.txt
odoo12_addon_stock_picking_filter_lot-12.0.1.1.2.dist-info/RECORD
