Metadata-Version: 2.1
Name: odoo12-addon-stock-picking-filter-lot
Version: 12.0.1.1.2
Summary: In picking out lots' selection, filter lots based on their location
Home-page: https://github.com/OCA/stock-logistics-workflow12.0/stock_filter_lot
Author: Agile Business Group, Odoo Community Association (OCA)
Author-email: support@odoo-community.org
License: AGPL-3
Platform: UNKNOWN
Classifier: Programming Language :: Python
Classifier: Framework :: Odoo
Classifier: Framework :: Odoo :: 12.0
Classifier: License :: OSI Approved :: GNU Affero General Public License v3
Requires-Python: >=3.5
Requires-Dist: odoo (<12.1dev,>=12.0a)
